e2enetworks/__init__.py
e2enetworks/constants.py
e2enetworks/cloud/__init__.py
e2enetworks/cloud/test.py
e2enetworks/cloud/tir/__init__.py
e2enetworks/cloud/tir/apitoken.py
e2enetworks/cloud/tir/client.py
e2enetworks/cloud/tir/constants.py
e2enetworks/cloud/tir/datasets.py
e2enetworks/cloud/tir/endpoints.py
e2enetworks/cloud/tir/helpers.py
e2enetworks/cloud/tir/images.py
e2enetworks/cloud/tir/minio_service.py
e2enetworks/cloud/tir/models.py
e2enetworks/cloud/tir/notebook.py
e2enetworks/cloud/tir/pipelines.py
e2enetworks/cloud/tir/projects.py
e2enetworks/cloud/tir/skus.py
e2enetworks/cloud/tir/teams.py
e2enetworks/cloud/tir/utils.py
e2enetworks/cloud/tir/version.py
e2enetworks-1.1.7.dist-info/LICENSE.txt
e2enetworks-1.1.7.dist-info/METADATA
e2enetworks-1.1.7.dist-info/WHEEL
e2enetworks-1.1.7.dist-info/top_level.txt
e2enetworks-1.1.7.dist-info/RECORD
