Metadata-Version: 2.1
Name: e2enetworks
Version: 1.1.7
Summary: E2E Networks Plugins
Author: Dhananjay Singh
Author-email: djs091298@gmail.com
License: MIT
Classifier: Development Status :: 3 - Alpha
Classifier: Environment :: Plugins
Classifier: Intended Audience :: System Administrators
Classifier: License :: OSI Approved :: Apache Software License
Classifier: Operating System :: POSIX :: Linux
Classifier: Programming Language :: Python
Classifier: Programming Language :: Python :: 2
Classifier: Programming Language :: Python :: 2.7
Classifier: Programming Language :: Python :: 3
Classifier: Programming Language :: Python :: 3.4
Classifier: Programming Language :: Python :: 3.5
Classifier: Programming Language :: Python :: 3.6
Classifier: Programming Language :: Python :: 3.7
Classifier: Topic :: Internet :: WWW/HTTP
Classifier: Topic :: Security
Classifier: Topic :: System :: Installation/Setup
Classifier: Topic :: System :: Networking
Classifier: Topic :: System :: Systems Administration
Classifier: Topic :: Utilities
Requires-Python: >=2.7, !=3.0.*, !=3.1.*, !=3.2.*, !=3.3.*
License-File: LICENSE.txt
Requires-Dist: requests (~=2.30.0)
Requires-Dist: urllib3 (==1.26.6)
Requires-Dist: kfp (==1.8.22)
Requires-Dist: kfp-pipeline-spec (==0.1.16)
Requires-Dist: kfp-server-api (==1.8.5)
Requires-Dist: minio (==7.1.3)
Requires-Dist: prettytable (==3.9.0)
